npp2nvm/__init__.py
npP2NVM-0.2.dist-info/LICENSE
npP2NVM-0.2.dist-info/METADATA
npP2NVM-0.2.dist-info/WHEEL
npP2NVM-0.2.dist-info/top_level.txt
npP2NVM-0.2.dist-info/RECORD
